crypto_licensing/__init__.py
crypto_licensing/__main__.py
crypto_licensing/cli.py
crypto_licensing/cli_test.py
crypto_licensing/crypto_test.py
crypto_licensing/ed25519_djb.py
crypto_licensing/misc.py
crypto_licensing/misc_test.py
crypto_licensing/version.py
crypto_licensing/x25519_test.py
crypto_licensing/ed25519/__init__.py
crypto_licensing/ed25519ll_pyonly/__init__.py
crypto_licensing/ed25519ll_pyonly/djbec.py
crypto_licensing/licensing/__init__.py
crypto_licensing/licensing/__main__.py
crypto_licensing/licensing/bitquery_test.py
crypto_licensing/licensing/defaults.py
crypto_licensing/licensing/doh_test.py
crypto_licensing/licensing/grant_test.py
crypto_licensing/licensing/licensing_test.py
crypto_licensing/licensing/main.py
crypto_licensing/licensing/verification.py
crypto_licensing/licensing/verification_test.py
crypto_licensing/licensing/doh/__init__.py
crypto_licensing/licensing/doh/__main__.py
crypto_licensing/licensing/doh/cli.py
crypto_licensing/licensing/static/txt/CL-KEYPAIR-MISSING.txt
crypto_licensing/x25519/__init__.py
crypto_licensing-5.2.3.dist-info/licenses/COPYING
crypto_licensing-5.2.3.dist-info/licenses/LICENSE
crypto_licensing-5.2.3.dist-info/METADATA
crypto_licensing-5.2.3.dist-info/WHEEL
crypto_licensing-5.2.3.dist-info/entry_points.txt
crypto_licensing-5.2.3.dist-info/top_level.txt
crypto_licensing-5.2.3.dist-info/zip-safe
crypto_licensing-5.2.3.dist-info/RECORD
