Metadata-Version: 2.4
Name: crypto_licensing
Version: 5.2.3
Summary: The crypto-licensing module implements Ed25519-signed license checking and automatic issuance after cryptocurrency payment
Home-page: https://github.com/pjkundert/crypto-licensing
Author: Perry Kundert
Author-email: perry@dominionrnd.com
License: Dual License; GPLv3 and Proprietary
Project-URL: Bug Tracker, https://github.com/pjkundert/crypto-licensing/issues
Keywords: licensing Bitcoin Ethereum cryptocurrency payments Ed25519 signatures
Classifier: License :: OSI Approved :: GNU General Public License v3 or later (GPLv3+)
Classifier: License :: Other/Proprietary License
Classifier: Programming Language :: Python :: 2
Classifier: Programming Language :: Python :: 3
Classifier: Development Status :: 5 - Production/Stable
Classifier: Intended Audience :: Developers
Classifier: Intended Audience :: Financial and Insurance Industry
Classifier: Environment :: Console
Classifier: Topic :: Security :: Cryptography
Classifier: Topic :: Office/Business :: Financial
License-File: LICENSE
License-File: COPYING
Requires-Dist: chacha20poly1305>=0.0.3
Requires-Dist: click
Requires-Dist: configparser>=4.0; python_version < "3.0"
Requires-Dist: dnspython
Requires-Dist: enum34>=1.1; python_version < "3.4"
Requires-Dist: future>=1
Requires-Dist: pathlib2>=2.3; python_version < "3.4"
Requires-Dist: pytz; python_version < "3.0"
Requires-Dist: pytz_deprecation_shim; python_version >= "3.9"
Requires-Dist: requests<3,>=2.20
Requires-Dist: requests-toolbelt>=1; python_version > "2"
Requires-Dist: tzlocal
Provides-Extra: dev
Requires-Dist: build; extra == "dev"
Requires-Dist: packaging; extra == "dev"
Requires-Dist: flake8; extra == "dev"
Requires-Dist: pip; extra == "dev"
Requires-Dist: pytest>=4.6; extra == "dev"
Requires-Dist: setuptools; extra == "dev"
Requires-Dist: wheel; extra == "dev"
Provides-Extra: server
Requires-Dist: web.py-update>=0.74; extra == "server"
Requires-Dist: wsgilog>=0.3; extra == "server"
Requires-Dist: legacy-cgi>=2.6; python_version >= "3.13" and extra == "server"
Requires-Dist: cpppo>=5.0.0; extra == "server"
Provides-Extra: all
Requires-Dist: wheel; extra == "all"
Requires-Dist: packaging; extra == "all"
Requires-Dist: wsgilog>=0.3; extra == "all"
Requires-Dist: legacy-cgi>=2.6; python_version >= "3.13" and extra == "all"
Requires-Dist: flake8; extra == "all"
Requires-Dist: pip; extra == "all"
Requires-Dist: pytest>=4.6; extra == "all"
Requires-Dist: setuptools; extra == "all"
Requires-Dist: build; extra == "all"
Requires-Dist: web.py-update>=0.74; extra == "all"
Requires-Dist: cpppo>=5.0.0; extra == "all"
Provides-Extra: tests
Requires-Dist: flake8; extra == "tests"
Requires-Dist: pytest>=4.6; extra == "tests"
Dynamic: author
Dynamic: author-email
Dynamic: classifier
Dynamic: description
Dynamic: description-content-type
Dynamic: home-page
Dynamic: keywords
Dynamic: license
Dynamic: license-file
Dynamic: project-url
Dynamic: provides-extra
Dynamic: requires-dist
Dynamic: summary
